tonrocketapisdk/__init__.py
tonrocketapisdk/rocket.py
tonrocketapisdk-1.0.3.dist-info/METADATA
tonrocketapisdk-1.0.3.dist-info/WHEEL
tonrocketapisdk-1.0.3.dist-info/top_level.txt
tonrocketapisdk-1.0.3.dist-info/RECORD
