Metadata-Version: 2.1
Name: tonrocketapisdk
Version: 1.0.3
Summary: UNKNOWN
Home-page: https://github.com/danya7423/tonRocket-api-sdk-py
Author: я
License: MIT
Platform: UNKNOWN
Classifier: Programming Language :: Python :: 3.6
Requires-Dist: requests
